pytdx/__init__.py
pytdx/tdx.py
pytdx/models/__init__.py
pytdx/models/asset.py
pytdx/models/attribute.py
pytdx/models/base_model.py
pytdx/models/knowledge_article.py
pytdx/models/ticket.py
tests/__init__.py
tests/test_tdx.py
tests/ticket_tests.py
py_teamdynamix-0.2.9.dist-info/LICENSE
py_teamdynamix-0.2.9.dist-info/METADATA
py_teamdynamix-0.2.9.dist-info/WHEEL
py_teamdynamix-0.2.9.dist-info/top_level.txt
py_teamdynamix-0.2.9.dist-info/RECORD
