Metadata-Version: 2.1
Name: py-teamdynamix
Version: 0.2.9
Summary: Python client for interacting with the TeamDynamix ITSM APIs
Author: Julien Rossow-Greenberg
Author-email: julien.rossowgreenberg@villanova.edu
Classifier: Programming Language :: Python :: 3
Classifier: License :: OSI Approved :: MIT License
Classifier: Operating System :: OS Independent
Requires: requests
Requires-Python: >=3.10
License-File: LICENSE
